tsforecast/__init__.py
tsforecast/_modidx.py
tsforecast/dataset.py
tsforecast/defaults.py
tsforecast/forecasting_pipeline.py
tsforecast/hp_search.py
tsforecast/model.py
tsforecast/time_transform.py
tsforecast/window_generator.py
tsforecast-0.0.1.dist-info/LICENSE
tsforecast-0.0.1.dist-info/METADATA
tsforecast-0.0.1.dist-info/WHEEL
tsforecast-0.0.1.dist-info/entry_points.txt
tsforecast-0.0.1.dist-info/top_level.txt
tsforecast-0.0.1.dist-info/RECORD
